[
    {
        "code": "ability",
        "name": "Ability"
    },
    {
        "code": "artillery",
        "name": "Artillery"
    },
    {
        "code": "bounty-hunter",
        "name": "Bounty Hunter"
    },
    {
        "code": "droid",
        "name": "Droid"
    },
    {
        "code": "equipment",
        "name": "Equipment"
    },
    {
        "code": "jawa",
        "name": "Jawa"
    },
    {
        "code": "jedi",
        "name": "Jedi"
    },
    {
        "code": "location",
        "name": "Location"
    },
    {
        "code": "pilot",
        "name": "Pilot"
    },
    {
        "code": "scoundrel",
        "name": "Scoundrel"
    },
    {
        "code": "title",
        "name": "Title"
    },
    {
        "code": "trooper",
        "name": "Trooper"
    },
    {
        "code": "vehicle",
        "name": "Vehicle"
    },
    {
        "code": "weapon",
        "name": "Weapon"
    },
    {
        "code": "witch",
        "name": "Witch"
    },
    {
        "code": "sith",
        "name": "Sith"
    },
    {
        "code": "leader",
        "name": "Leader"
    },
    {
        "code": "gungan",
        "name": "Gungan"
    },
    {
        "code": "artillery",
        "name": "Artillery"
    }
]
